README
server.py
setup.cfg
setup.py
AutomodelServerModules/AlignFile.py
AutomodelServerModules/AlignmentBuilder.py
AutomodelServerModules/PirFile.py
AutomodelServerModules/PirFormat.py
AutomodelServerModules/__init__.py
AutomodelServerModules/file.py
AutomodelServerModules/fixpdb.py
AutomodelServerModules/loader2.py
AutomodelServerModules/pdb.py
AutomodelServerModules/pdb_test.py
AutomodelServerModules/sequence.py
automodel_server.egg-info/PKG-INFO
automodel_server.egg-info/SOURCES.txt
automodel_server.egg-info/dependency_links.txt
automodel_server.egg-info/requires.txt
automodel_server.egg-info/top_level.txt
modellerstep/Align.py
modellerstep/GetDataFromPDB.py
modellerstep/GetProt.py
modellerstep/GetProt2.py
modellerstep/Loop_Refinement.py
modellerstep/MakeProfile.py
modellerstep/Malign.py
modellerstep/Malign2.py
modellerstep/Modeller.py
modellerstep/Modeller_Caller.py
modellerstep/Mold.py
modellerstep/Procheck_Evaluate.py
modellerstep/RunCommand.py
modellerstep/__init__.py
modellingfile/PirSequence.py
modellingfile/__init__.py
pdb/__init__.py
pdb/pdb_95.bin
pdb/pdb_95.pir
tests/__init__.py