Metadata-Version: 1.0
Name: automodel-server
Version: 0.1.14
Summary: Server of service for structure protein prediction
Home-page: https://bitbucket.org/jlalmeidaf/automodel-server-with-hmmer
Author: João Luiz de Almeida Filho, Jorge Hernandez Fernandez
Author-email: joaoluiz.af@gmail.com
License: UNKNOWN
Keywords: protein modeling modeller automodel
Platform: UNKNOWN
